{
  "id": "great-white-shark-guadalupe",
  "slug": "great-white-shark-guadalupe",
  "species": {
    "commonName": "Great White Shark",
    "scientificName": "Carcharodon carcharias",
    "family": "Lamnidae",
    "maxWeight": "2,268 kg",
    "maxWeightKg": 2268,
    "maxLength": "6.4 m",
    "maxLengthCm": 640,
    "waterType": "saltwater",
    "conservationStatus": "Vulnerable",
    "habitat": "Coastal and offshore waters",
    "distribution": "Worldwide in temperate waters",
    "description": "The great white shark is a species of large lamniform shark.",
    "funFacts": [
      "Up to 300 serrated teeth.",
      "Can sense blood from miles away."
    ],
    "image": "https://upload.wikimedia.org/wikipedia/commons/5/56/White_shark.jpg",
    "imageCredit": "Wikimedia Commons",
    "tags": [
      "shark",
      "predator",
      "saltwater"
    ],
    "speciesSlug": "great-white-shark"
  },
  "location": {
    "name": "Guadalupe Island",
    "country": "Mexico",
    "countryCode": "ME",
    "region": "Global Hotspot",
    "continent": "Worldwide",
    "lat": 29.0323,
    "lng": -118.2721,
    "waterType": "saltwater",
    "waterBody": "Ocean"
  },
  "fishing": {
    "isAllowed": true,
    "permitRequired": true,
    "notes": "World-class destination for Great White Shark.",
    "regulations": "Local fishing laws apply. Catch and release encouraged for Great White Shark.",
    "regulationSource": "https://www.google.com/search?q=fishing+regulations+Guadalupe+Island"
  },
  "content": {
    "title": "Giant Great White Shark at Guadalupe Island, Mexico",
    "metaDescription": "Discover the best place to find Great White Shark in Guadalupe Island. Maps, facts, and fishing info.",
    "description": "The Guadalupe Island in Mexico is legendary among trophy hunters for its massive Great White Shark. Specimens here are known for their exceptional size and strength.",
    "highlights": [
      "World record potential.",
      "Stunning natural beauty.",
      "Expert guides available."
    ],
    "bestTime": "Varies by season",
    "difficulty": "Hard"
  },
  "media": {
    "heroImage": "https://upload.wikimedia.org/wikipedia/commons/5/56/White_shark.jpg",
    "heroImageAlt": "Great White Shark",
    "gallery": [],
    "imageCredits": "Wikimedia Commons"
  },
  "sources": [
    {
      "name": "Wikipedia",
      "url": "https://en.wikipedia.org/wiki/Great_White_Shark",
      "accessedDate": "2026-05-02"
    }
  ],
  "tags": [
    "shark",
    "predator",
    "saltwater",
    "mexico"
  ],
  "publishedAt": "2026-05-02",
  "updatedAt": "2026-05-02",
  "featured": false,
  "priority": 5
}