{
  "id": "wahoo-230",
  "slug": "wahoo-230",
  "species": {
    "commonName": "Wahoo",
    "scientificName": "Acanthocybium solandri",
    "maxWeightKg": 80,
    "waterType": "saltwater",
    "description": "The Wahoo is one of the most sought-after game fish in Europe.",
    "image": "https://images.unsplash.com/photo-1533481405265-e9ce0c044abb?auto=format&fit=crop&q=80&w=1200"
  },
  "location": {
    "name": "Legendary Wahoo Spot 230",
    "country": "Mexico",
    "continent": "Europe",
    "lat": -89.09511228456512,
    "lng": 77.39253696198773
  },
  "content": {
    "title": "Chasing Giant Wahoo in Mexico",
    "description": "Experience the thrill of catching massive Wahoo in the heart of Mexico.",
    "bestTime": "Spring/Summer"
  },
  "fishing": {
    "regulations": "Local limits apply. Always check with local authorities.",
    "isAllowed": true
  },
  "media": {
    "heroImage": "https://images.unsplash.com/photo-1517430816045-df4b7de11d1d?auto=format&fit=crop&q=80&w=1200"
  },
  "sources": [
    {
      "name": "Global Fishing Data",
      "url": "https://example.com"
    }
  ],
  "contentType": "report",
  "featured": true
}